x_transformers_rl/__init__.py
x_transformers_rl/distributed.py
x_transformers_rl/evolution.py
x_transformers_rl/x_transformers_rl.py
x_transformers_rl-0.0.99.dist-info/METADATA
x_transformers_rl-0.0.99.dist-info/WHEEL
x_transformers_rl-0.0.99.dist-info/licenses/LICENSE
x_transformers_rl-0.0.99.dist-info/RECORD
