Metadata-Version: 2.4
Name: x-transformers-rl
Version: 0.0.99
Summary: X-Transformer for RL
Project-URL: Homepage, https://pypi.org/project/x-transformers-rl/
Project-URL: Repository, https://github.com/lucidrains/x-transformers-rl
Author-email: Phil Wang <lucidrains@gmail.com>
License: MIT License
License-File: LICENSE
Keywords: artificial intelligence,deep learning,evolution,reinforcement learning,transformers
Classifier: Development Status :: 4 - Beta
Classifier: Intended Audience :: Developers
Classifier: License :: OSI Approved :: MIT License
Classifier: Programming Language :: Python :: 3.8
Classifier: Topic :: Scientific/Engineering :: Artificial Intelligence
Requires-Python: >=3.8
Requires-Dist: accelerate
Requires-Dist: adam-atan2-pytorch
Requires-Dist: assoc-scan
Requires-Dist: einops>=0.8.0
Requires-Dist: einx>=0.3.0
Requires-Dist: ema-pytorch
Requires-Dist: hl-gauss-pytorch>=0.1.22
Requires-Dist: torch>=2.5
Requires-Dist: tqdm
Requires-Dist: vector-quantize-pytorch>=1.22.6
Requires-Dist: x-mlps-pytorch>=0.0.20
Requires-Dist: x-transformers>=2.3.21
Provides-Extra: test
Requires-Dist: pytest; extra == 'test'
